pyuntype_cli/__init__.py
pyuntype_cli/main.py
pyuntype_cli/utils/__init__.py
pyuntype_cli/utils/remover.py
pyuntype_cli/utils/title.py
pyuntype-0.0.3.dist-info/entry_points.txt
pyuntype-0.0.3.dist-info/LICENSE
pyuntype-0.0.3.dist-info/WHEEL
pyuntype-0.0.3.dist-info/METADATA
pyuntype-0.0.3.dist-info/RECORD
