Metadata-Version: 2.1
Name: pyuntype
Version: 0.0.3
Summary: Programatically untype your Python code
Home-page: https://escape.tech/
License: Apache-2.0
Author: Escape Technologies SAS
Author-email: ping@escape.tech
Maintainer: Antoine Carossio
Maintainer-email: antoine.carossio@me.com
Requires-Python: >=3.9,<4.0
Classifier: License :: OSI Approved :: Apache Software License
Classifier: License :: OSI Approved :: MIT License
Classifier: Operating System :: OS Independent
Classifier: Programming Language :: Python :: 3
Classifier: Programming Language :: Python :: 3.9
Requires-Dist: astor (>=0.8.1,<0.9.0)
Requires-Dist: click (>=7.1.2,<8.0.0)
Requires-Dist: loguru (>=0.5.3,<0.6.0)
Requires-Dist: pydash (>=5.0.0,<6.0.0)
Project-URL: Bug Tracker, https://github.com/Escape-Technologies/pyuntype/issues
Project-URL: Repository, https://github.com/Escape-Technologies/pyuntype
